xbs_test_uiautomator2/__init__.py
xbs_test_uiautomator2/uiautomator2.py
xbs_test_uiautomator2-0.1.3.dist-info/METADATA
xbs_test_uiautomator2-0.1.3.dist-info/WHEEL
xbs_test_uiautomator2-0.1.3.dist-info/top_level.txt
xbs_test_uiautomator2-0.1.3.dist-info/RECORD
