Metadata-Version: 2.1
Name: xbs-test-uiautomator2
Version: 0.1.3
Summary: rewrite uiautomator2
Home-page: https://github.com/ll6566/xbsUiautomator2
Author: 65
Author-email: 18974710587@163.com
License: MIT
Platform: UNKNOWN
Classifier: Programming Language :: Python :: 3
Classifier: License :: OSI Approved :: MIT License
Classifier: Operating System :: OS Independent
Requires-Python: >=3.0.0
Requires-Dist: uiautomator2==2.16.25
